fbv/__init__.py
fbv/decorators.py
fbv/middleware.py
fbv/views.py
django_fbv-0.5.1.dist-info/LICENSE
django_fbv-0.5.1.dist-info/WHEEL
django_fbv-0.5.1.dist-info/METADATA
django_fbv-0.5.1.dist-info/RECORD
