Metadata-Version: 2.1
Name: django-fbv
Version: 0.5.1
Summary: Utilities to make function-based views cleaner, more efficient, and better tasting. 
Home-page: https://github.com/adamghill/django-fbv/
License: BSD-3
Keywords: python,html,django
Author: adamghill
Author-email: adam@adamghill.com
Requires-Python: >=3.7,<4.0
Classifier: License :: Other/Proprietary License
Classifier: Programming Language :: Python :: 3
Classifier: Programming Language :: Python :: 3.10
Classifier: Programming Language :: Python :: 3.7
Classifier: Programming Language :: Python :: 3.8
Classifier: Programming Language :: Python :: 3.9
Provides-Extra: docs
Requires-Dist: Sphinx (>=4.3.2,<5.0.0); extra == "docs"
Requires-Dist: attrs (>=21.4.0,<22.0.0); extra == "docs"
Requires-Dist: django (>2.2.0)
Requires-Dist: furo (>=2021.11.23,<2022.0.0); extra == "docs"
Requires-Dist: linkify-it-py (>=1.0.3,<2.0.0); extra == "docs"
Requires-Dist: myst-parser (>=0.16.1,<0.17.0); extra == "docs"
Requires-Dist: sphinx-copybutton (>=0.4.0,<0.5.0); extra == "docs"
Requires-Dist: toml; extra == "docs"
Project-URL: Documentation, https://django-fbv.readthedocs.io/
Project-URL: Funding, https://github.com/sponsors/adamghill
Project-URL: Repository, https://github.com/adamghill/django-fbv/
